pytest_openapi/__init__.py
pytest_openapi/case_generator.py
pytest_openapi/contract.py
pytest_openapi/openapi.py
pytest_openapi/plugin.py
pytest_openapi-0.1.4.dist-info/licenses/LICENSE
pytest_openapi-0.1.4.dist-info/METADATA
pytest_openapi-0.1.4.dist-info/WHEEL
pytest_openapi-0.1.4.dist-info/entry_points.txt
pytest_openapi-0.1.4.dist-info/top_level.txt
pytest_openapi-0.1.4.dist-info/RECORD
